Workbook

Sheet Sheet1
B3: Column Labels
B4: Beauty | C4: Electronics | D4: Fashion | E4: Home | F4: Sports | G4: Grand Total
A5: Sum of Revenue | B5: 127646.15 | C5: 163629.25 | D5: 136503.85 | E5: 126172 | F5: 147431.3 | G5: 701382.55

Sheet Sheet2
A3: Row Labels | B3: Count of Order_ID
A4: no | B4: 170
A5: yes | B5: 330
A6: (blank)
A7: Grand Total | B7: 500

Sheet Sheet3
A3: Row Labels | B3: Count of Revenue
A4: Jan | B4: 25
A5: Feb | B5: 40
A6: Mar | B6: 20
A7: Apr | B7: 45
A8: May | B8: 37
A9: Jun | B9: 38
A10: Jul | B10: 29
A11: Aug | B11: 41
A12: Sep | B12: 35
A13: Oct | B13: 36
A14: Nov | B14: 32
A15: Dec | B15: 32
A16: Grand Total | B16: 410

Sheet raw data
A1: Order_ID | B1: Order_Date | C1: Customer_ID | D1: Category | E1: Product | F1: Quantity | G1: Price | H1: Discount | I1: Revenue | J1: high value order | K1: Discounted orders | L1: Repeated customer | M1: High discount orders | N1: Vip customers | O1: customer total revenue | P1: outliner flag
A2: O10000 | B2: 45029 | C2: C101 | D2: Home | E2: P59 | F2: 2 | G2: 199 | H2: 10 | I2: 358.2 | J2: =IF(I2>formulas!$B$5,"yes","no") -> no | K2: =IF(H2>0,"yes","no") -> yes | L2: =IF(COUNTIF('raw data'!$B$2:$B$501,B2)>1,"Yes","No") -> Yes | M2: =IF(H2>15,"yes","no") -> no | N2: =IF(AND(L2="Yes", J2="yes" ),"Yes","No") -> No | O2: =SUMIF('raw data'!B$2:B$501,B2,'raw data'!I$2:I$501) -> 3914.8 | P2: =IF(OR(I2<Visualization!$B$6,I2>Visualization!$B$7),"Outlier","Normal") -> Outlier
A3: O10001 | B3: 45275 | C3: C191 | D3: Beauty | E3: P37 | F3: 2 | G3: 199 | H3: 15 | I3: 358.2 | J3: =IF(I3>formulas!$B$5,"yes","no") -> no | K3: =IF(H3>0,"yes","no") -> yes | L3: =IF(COUNTIF('raw data'!$B$2:$B$501,B3)>1,"Yes","No") -> Yes | M3: =IF(H3>15,"yes","no") -> no | N3: =IF(AND(L3="Yes", J3="yes" ),"Yes","No") -> No | O3: =SUMIF('raw data'!B$2:B$501,B3,'raw data'!I$2:I$501) -> 7282.8 | P3: =IF(OR(I3<Visualization!$B$6,I3>Visualization!$B$7),"Outlier","Normal") -> Outlier
A4: O10002 | B4: 45197 | C4: C131 | D4: Electronics | E4: P61 | F4: 2 | G4: 299 | H4: 5 | I4: 358.2 | J4: =IF(I4>formulas!$B$5,"yes","no") -> no | K4: =IF(H4>0,"yes","no") -> yes | L4: =IF(COUNTIF('raw data'!$B$2:$B$501,B4)>1,"Yes","No") -> Yes | M4: =IF(H4>15,"yes","no") -> no | N4: =IF(AND(L4="Yes", J4="yes" ),"Yes","No") -> No | O4: =SUMIF('raw data'!B$2:B$501,B4,'raw data'!I$2:I$501) -> 3556.6 | P4: =IF(OR(I4<Visualization!$B$6,I4>Visualization!$B$7),"Outlier","Normal") -> Outlier
A5: O10003 | B5: 45033 | C5: C190 | D5: Home | E5: P43 | F5: 3 | H5: 0 | I5: 358.2 | J5: =IF(I5>formulas!$B$5,"yes","no") -> no | K5: =IF(H5>0,"yes","no") -> no | L5: =IF(COUNTIF('raw data'!$B$2:$B$501,B5)>1,"Yes","No") -> No | M5: =IF(H5>15,"yes","no") -> no | N5: =IF(AND(L5="Yes", J5="yes" ),"Yes","No") -> No | O5: =SUMIF('raw data'!B$2:B$501,B5,'raw data'!I$2:I$501) -> 358.2 | P5: =IF(OR(I5<Visualization!$B$6,I5>Visualization!$B$7),"Outlier","Normal") -> Outlier | AA5: q1 = quartile.inc(i2:i501,1)
A6: O10004 | B6: 44998 | C6: C183 | D6: Electronics | E6: P70 | F6: 1 | G6: 199 | I6: 358.2 | J6: =IF(I6>formulas!$B$5,"yes","no") -> no | K6: =IF(H6>0,"yes","no") -> no | L6: =IF(COUNTIF('raw data'!$B$2:$B$501,B6)>1,"Yes","No") -> No | M6: =IF(H6>15,"yes","no") -> no | N6: =IF(AND(L6="Yes", J6="yes" ),"Yes","No") -> No | O6: =SUMIF('raw data'!B$2:B$501,B6,'raw data'!I$2:I$501) -> 358.2 | P6: =IF(OR(I6<Visualization!$B$6,I6>Visualization!$B$7),"Outlier","Normal") -> Outlier | U6: =COUNTIF(P2:P501,"outlier") -> 393
A7: O10005 | B7: 45115 | C7: C123 | D7: Fashion | E7: P39 | F7: 2 | G7: 999 | H7: 20 | I7: 358.2 | J7: =IF(I7>formulas!$B$5,"yes","no") -> no | K7: =IF(H7>0,"yes","no") -> yes | L7: =IF(COUNTIF('raw data'!$B$2:$B$501,B7)>1,"Yes","No") -> Yes | M7: =IF(H7>15,"yes","no") -> yes | N7: =IF(AND(L7="Yes", J7="yes" ),"Yes","No") -> No | O7: =SUMIF('raw data'!B$2:B$501,B7,'raw data'!I$2:I$501) -> 756.2 | P7: =IF(OR(I7<Visualization!$B$6,I7>Visualization!$B$7),"Outlier","Normal") -> Outlier
A8: O10006 | B8: 44947 | C8: C111 | D8: Home | E8: P56 | F8: 3 | G8: 1499 | H8: 10 | I8: 358.2 | J8: =IF(I8>formulas!$B$5,"yes","no") -> no | K8: =IF(H8>0,"yes","no") -> yes | L8: =IF(COUNTIF('raw data'!$B$2:$B$501,B8)>1,"Yes","No") -> Yes | M8: =IF(H8>15,"yes","no") -> no | N8: =IF(AND(L8="Yes", J8="yes" ),"Yes","No") -> No | O8: =SUMIF('raw data'!B$2:B$501,B8,'raw data'!I$2:I$501) -> 1782.25 | P8: =IF(OR(I8<Visualization!$B$6,I8>Visualization!$B$7),"Outlier","Normal") -> Outlier
A9: O10007 | B9: 45029 | C9: C149 | D9: Fashion | E9: P63 | F9: 5 | G9: 1999 | H9: 0 | I9: 358.2 | J9: =IF(I9>formulas!$B$5,"yes","no") -> no | K9: =IF(H9>0,"yes","no") -> no | L9: =IF(COUNTIF('raw data'!$B$2:$B$501,B9)>1,"Yes","No") -> Yes | M9: =IF(H9>15,"yes","no") -> no | N9: =IF(AND(L9="Yes", J9="yes" ),"Yes","No") -> No | O9: =SUMIF('raw data'!B$2:B$501,B9,'raw data'!I$2:I$501) -> 3914.8 | P9: =IF(OR(I9<Visualization!$B$6,I9>Visualization!$B$7),"Outlier","Normal") -> Outlier
A10: O10008 | B10: 45048 | C10: C134 | D10: Home | E10: P46 | F10: 1 | G10: 299 | H10: 20 | I10: 358.2 | J10: =IF(I10>formulas!$B$5,"yes","no") -> no | K10: =IF(H10>0,"yes","no") -> yes | L10: =IF(COUNTIF('raw data'!$B$2:$B$501,B10)>1,"Yes","No") -> Yes | M10: =IF(H10>15,"yes","no") -> yes | N10: =IF(AND(L10="Yes", J10="yes" ),"Yes","No") -> No | O10: =SUMIF('raw data'!B$2:B$501,B10,'raw data'!I$2:I$501) -> 358.2 | P10: =IF(OR(I10<Visualization!$B$6,I10>Visualization!$B$7),"Outlier","Normal") -> Outlier
A11: O10009 | B11: 45141 | C11: C132 | D11: Sports | E11: P88 | F11: 2 | G11: 299 | H11: 20 | I11: 358.2 | J11: =IF(I11>formulas!$B$5,"yes","no") -> no | K11: =IF(H11>0,"yes","no") -> yes | L11: =IF(COUNTIF('raw data'!$B$2:$B$501,B11)>1,"Yes","No") -> Yes | M11: =IF(H11>15,"yes","no") -> yes | N11: =IF(AND(L11="Yes", J11="yes" ),"Yes","No") -> No | O11: =SUMIF('raw data'!B$2:B$501,B11,'raw data'!I$2:I$501) -> 4252.4 | P11: =IF(OR(I11<Visualization!$B$6,I11>Visualization!$B$7),"Outlier","Normal") -> Outlier
A12: O10010 | B12: 45257 | C12: C132 | D12: Beauty | E12: P11 | F12: 2 | G12: 199 | I12: 358.2 | J12: =IF(I12>formulas!$B$5,"yes","no") -> no | K12: =IF(H12>0,"yes","no") -> no | L12: =IF(COUNTIF('raw data'!$B$2:$B$501,B12)>1,"Yes","No") -> Yes | M12: =IF(H12>15,"yes","no") -> no | N12: =IF(AND(L12="Yes", J12="yes" ),"Yes","No") -> No | O12: =SUMIF('raw data'!B$2:B$501,B12,'raw data'!I$2:I$501) -> 1780.35 | P12: =IF(OR(I12<Visualization!$B$6,I12>Visualization!$B$7),"Outlier","Normal") -> Outlier
A13: O10011 | B13: 45014 | C13: C160 | D13: Sports | E13: P62 | F13: 3 | H13: 15 | I13: 358.2 | J13: =IF(I13>formulas!$B$5,"yes","no") -> no | K13: =IF(H13>0,"yes","no") -> yes | L13: =IF(COUNTIF('raw data'!$B$2:$B$501,B13)>1,"Yes","No") -> No | M13: =IF(H13>15,"yes","no") -> no | N13: =IF(AND(L13="Yes", J13="yes" ),"Yes","No") -> No | O13: =SUMIF('raw data'!B$2:B$501,B13,'raw data'!I$2:I$501) -> 358.2 | P13: =IF(OR(I13<Visualization!$B$6,I13>Visualization!$B$7),"Outlier","Normal") -> Outlier
A14: O10012 | B14: 45026 | C14: C150 | D14: Fashion | E14: P77 | F14: 2 | G14: 999 | I14: 358.2 | J14: =IF(I14>formulas!$B$5,"yes","no") -> no | K14: =IF(H14>0,"yes","no") -> no | L14: =IF(COUNTIF('raw data'!$B$2:$B$501,B14)>1,"Yes","No") -> Yes | M14: =IF(H14>15,"yes","no") -> no | N14: =IF(AND(L14="Yes", J14="yes" ),"Yes","No") -> No | O14: =SUMIF('raw data'!B$2:B$501,B14,'raw data'!I$2:I$501) -> 2024.35 | P14: =IF(OR(I14<Visualization!$B$6,I14>Visualization!$B$7),"Outlier","Normal") -> Outlier
A15: O10013 | B15: 45286 | C15: C142 | D15: Beauty | E15: P98 | F15: 2 | H15: 15 | J15: =IF(I15>formulas!$B$5,"yes","no") -> no | K15: =IF(H15>0,"yes","no") -> yes | L15: =IF(COUNTIF('raw data'!$B$2:$B$501,B15)>1,"Yes","No") -> Yes | M15: =IF(H15>15,"yes","no") -> no | N15: =IF(AND(L15="Yes", J15="yes" ),"Yes","No") -> No | O15: =SUMIF('raw data'!B$2:B$501,B15,'raw data'!I$2:I$501) -> 11794.1 | P15: =IF(OR(I15<Visualization!$B$6,I15>Visualization!$B$7),"Outlier","Normal") -> Normal | T15: 0 | U15: {=FREQUENCY(I2:I501,T15:T22)} -> 17
A16: O10014 | B16: 45078 | C16: C111 | D16: Home | E16: P25 | F16: 4 | G16: 499 | H16: 15 | I16: 1696.6 | J16: =IF(I16>formulas!$B$5,"yes","no") -> yes | K16: =IF(H16>0,"yes","no") -> yes | L16: =IF(COUNTIF('raw data'!$B$2:$B$501,B16)>1,"Yes","No") -> Yes | M16: =IF(H16>15,"yes","no") -> no | N16: =IF(AND(L16="Yes", J16="yes" ),"Yes","No") -> Yes | O16: =SUMIF('raw data'!B$2:B$501,B16,'raw data'!I$2:I$501) -> 5519.05 | P16: =IF(OR(I16<Visualization!$B$6,I16>Visualization!$B$7),"Outlier","Normal") -> Outlier | T16: 500
A17: O10015 | B17: 45057 | C17: C166 | D17: Beauty | E17: P71 | F17: 3 | G17: 499 | H17: 0 | I17: 1497 | J17: =IF(I17>formulas!$B$5,"yes","no") -> yes | K17: =IF(H17>0,"yes","no") -> no | L17: =IF(COUNTIF('raw data'!$B$2:$B$501,B17)>1,"Yes","No") -> Yes | M17: =IF(H17>15,"yes","no") -> no | N17: =IF(AND(L17="Yes", J17="yes" ),"Yes","No") -> Yes | O17: =SUMIF('raw data'!B$2:B$501,B17,'raw data'!I$2:I$501) -> 2495 | P17: =IF(OR(I17<Visualization!$B$6,I17>Visualization!$B$7),"Outlier","Normal") -> Outlier | T17: 1000
A18: O10016 | B18: 45076 | C18: C164 | D18: Electronics | E18: P52 | F18: 2 | G18: 1499 | H18: 0 | I18: 2998 | J18: =IF(I18>formulas!$B$5,"yes","no") -> yes | K18: =IF(H18>0,"yes","no") -> no | L18: =IF(COUNTIF('raw data'!$B$2:$B$501,B18)>1,"Yes","No") -> Yes | M18: =IF(H18>15,"yes","no") -> no | N18: =IF(AND(L18="Yes", J18="yes" ),"Yes","No") -> Yes | O18: =SUMIF('raw data'!B$2:B$501,B18,'raw data'!I$2:I$501) -> 2998 | P18: =IF(OR(I18<Visualization!$B$6,I18>Visualization!$B$7),"Outlier","Normal") -> Outlier | T18: 2000
A19: O10017 | B19: 45235 | C19: C132 | D19: Beauty | E19: P4 | F19: 4 | G19: 199 | H19: 10 | I19: 716.4 | J19: =IF(I19>formulas!$B$5,"yes","no") -> no | K19: =IF(H19>0,"yes","no") -> yes | L19: =IF(COUNTIF('raw data'!$B$2:$B$501,B19)>1,"Yes","No") -> No | M19: =IF(H19>15,"yes","no") -> no | N19: =IF(AND(L19="Yes", J19="yes" ),"Yes","No") -> No | O19: =SUMIF('raw data'!B$2:B$501,B19,'raw data'!I$2:I$501) -> 716.4 | P19: =IF(OR(I19<Visualization!$B$6,I19>Visualization!$B$7),"Outlier","Normal") -> Outlier | T19: 3000
A20: O10018 | B20: 45184 | C20: C139 | D20: Electronics | E20: P59 | F20: 3 | G20: 199 | H20: 15 | I20: 507.45 | J20: =IF(I20>formulas!$B$5,"yes","no") -> no | K20: =IF(H20>0,"yes","no") -> yes | L20: =IF(COUNTIF('raw data'!$B$2:$B$501,B20)>1,"Yes","No") -> No | M20: =IF(H20>15,"yes","no") -> no | N20: =IF(AND(L20="Yes", J20="yes" ),"Yes","No") -> No | O20: =SUMIF('raw data'!B$2:B$501,B20,'raw data'!I$2:I$501) -> 507.45 | P20: =IF(OR(I20<Visualization!$B$6,I20>Visualization!$B$7),"Outlier","Normal") -> Outlier | T20: 5000
A21: O10019 | B21: 45270 | C21: C173 | D21: Beauty | E21: P72 | F21: 2 | G21: 199 | H21: 20 | I21: 318.4 | J21: =IF(I21>formulas!$B$5,"yes","no") -> no | K21: =IF(H21>0,"yes","no") -> yes | L21: =IF(COUNTIF('raw data'!$B$2:$B$501,B21)>1,"Yes","No") -> Yes | M21: =IF(H21>15,"yes","no") -> yes | N21: =IF(AND(L21="Yes", J21="yes" ),"Yes","No") -> No | O21: =SUMIF('raw data'!B$2:B$501,B21,'raw data'!I$2:I$501) -> 4815.4 | P21: =IF(OR(I21<Visualization!$B$6,I21>Visualization!$B$7),"Outlier","Normal") -> Outlier | T21: 8000
A22: O10020 | B22: 45220 | C22: C142 | D22: Electronics | E22: P20 | F22: 0 | G22: 1499 | H22: 5 | I22: 0 | J22: =IF(I22>formulas!$B$5,"yes","no") -> no | K22: =IF(H22>0,"yes","no") -> yes | L22: =IF(COUNTIF('raw data'!$B$2:$B$501,B22)>1,"Yes","No") -> Yes | M22: =IF(H22>15,"yes","no") -> no | N22: =IF(AND(L22="Yes", J22="yes" ),"Yes","No") -> No | O22: =SUMIF('raw data'!B$2:B$501,B22,'raw data'!I$2:I$501) -> 3398.3 | P22: =IF(OR(I22<Visualization!$B$6,I22>Visualization!$B$7),"Outlier","Normal") -> Normal | T22: 12000
A23: O10021 | B23: 45118 | C23: C143 | D23: Fashion | E23: P93 | G23: 499 | H23: 10 | J23: =IF(I23>formulas!$B$5,"yes","no") -> no | K23: =IF(H23>0,"yes","no") -> yes | L23: =IF(COUNTIF('raw data'!$B$2:$B$501,B23)>1,"Yes","No") -> Yes | M23: =IF(H23>15,"yes","no") -> no | N23: =IF(AND(L23="Yes", J23="yes" ),"Yes","No") -> No | O23: =SUMIF('raw data'!B$2:B$501,B23,'raw data'!I$2:I$501) -> 0 | P23: =IF(OR(I23<Visualization!$B$6,I23>Visualization!$B$7),"Outlier","Normal") -> Normal
A24: O10022 | B24: 45203 | C24: C128 | D24: Sports | E24: P63 | F24: 1 | H24: 0 | J24: =IF(I24>formulas!$B$5,"yes","no") -> no | K24: =IF(H24>0,"yes","no") -> no | L24: =IF(COUNTIF('raw data'!$B$2:$B$501,B24)>1,"Yes","No") -> Yes | M24: =IF(H24>15,"yes","no") -> no | N24: =IF(AND(L24="Yes", J24="yes" ),"Yes","No") -> No | O24: =SUMIF('raw data'!B$2:B$501,B24,'raw data'!I$2:I$501) -> 3598.2 | P24: =IF(OR(I24<Visualization!$B$6,I24>Visualization!$B$7),"Outlier","Normal") -> Normal
A25: O10023 | B25: 45087 | C25: C112 | D25: Home | E25: P54 | F25: 1 | G25: 1499 | I25: 1499 | J25: =IF(I25>formulas!$B$5,"yes","no") -> yes | K25: =IF(H25>0,"yes","no") -> no | L25: =IF(COUNTIF('raw data'!$B$2:$B$501,B25)>1,"Yes","No") -> Yes | M25: =IF(H25>15,"yes","no") -> no | N25: =IF(AND(L25="Yes", J25="yes" ),"Yes","No") -> Yes | O25: =SUMIF('raw data'!B$2:B$501,B25,'raw data'!I$2:I$501) -> 9893 | P25: =IF(OR(I25<Visualization!$B$6,I25>Visualization!$B$7),"Outlier","Normal") -> Outlier
A26: O10024 | B26: 45240 | C26: C111 | D26: Beauty | E26: P74 | F26: 1 | G26: 1499 | H26: 10 | I26: 1349.1 | J26: =IF(I26>formulas!$B$5,"yes","no") -> no | K26: =IF(H26>0,"yes","no") -> yes | L26: =IF(COUNTIF('raw data'!$B$2:$B$501,B26)>1,"Yes","No") -> Yes | M26: =IF(H26>15,"yes","no") -> no | N26: =IF(AND(L26="Yes", J26="yes" ),"Yes","No") -> No | O26: =SUMIF('raw data'!B$2:B$501,B26,'raw data'!I$2:I$501) -> 1349.1 | P26: =IF(OR(I26<Visualization!$B$6,I26>Visualization!$B$7),"Outlier","Normal") -> Outlier
A27: O10025 | B27: 44948 | C27: C194 | D27: Sports | E27: P98 | F27: 3 | H27: 10 | J27: =IF(I27>formulas!$B$5,"yes","no") -> no | K27: =IF(H27>0,"yes","no") -> yes | L27: =IF(COUNTIF('raw data'!$B$2:$B$501,B27)>1,"Yes","No") -> Yes | M27: =IF(H27>15,"yes","no") -> no | N27: =IF(AND(L27="Yes", J27="yes" ),"Yes","No") -> No | O27: =SUMIF('raw data'!B$2:B$501,B27,'raw data'!I$2:I$501) -> 1699.15 | P27: =IF(OR(I27<Visualization!$B$6,I27>Visualization!$B$7),"Outlier","Normal") -> Normal
A28: O10026 | B28: 45179 | C28: C145 | D28: Home | E28: P57 | F28: 1 | G28: 199 | H28: 10 | I28: 179.1 | J28: =IF(I28>formulas!$B$5,"yes","no") -> no | K28: =IF(H28>0,"yes","no") -> yes | L28: =IF(COUNTIF('raw data'!$B$2:$B$501,B28)>1,"Yes","No") -> Yes | M28: =IF(H28>15,"yes","no") -> no | N28: =IF(AND(L28="Yes", J28="yes" ),"Yes","No") -> No | O28: =SUMIF('raw data'!B$2:B$501,B28,'raw data'!I$2:I$501) -> 717.3 | P28: =IF(OR(I28<Visualization!$B$6,I28>Visualization!$B$7),"Outlier","Normal") -> Outlier
A29: O10027 | B29: 45162 | C29: C101 | D29: Home | E29: P90 | F29: 1 | G29: 999 | H29: 10 | I29: 899.1 | J29: =IF(I29>formulas!$B$5,"yes","no") -> no | K29: =IF(H29>0,"yes","no") -> yes | L29: =IF(COUNTIF('raw data'!$B$2:$B$501,B29)>1,"Yes","No") -> No | M29: =IF(H29>15,"yes","no") -> no | N29: =IF(AND(L29="Yes", J29="yes" ),"Yes","No") -> No | O29: =SUMIF('raw data'!B$2:B$501,B29,'raw data'!I$2:I$501) -> 899.1 | P29: =IF(OR(I29<Visualization!$B$6,I29>Visualization!$B$7),"Outlier","Normal") -> Outlier
A30: O10028 | B30: 45271 | C30: C134 | D30: Electronics | E30: P41 | F30: 1 | H30: 5 | J30: =IF(I30>formulas!$B$5,"yes","no") -> no | K30: =IF(H30>0,"yes","no") -> yes | L30: =IF(COUNTIF('raw data'!$B$2:$B$501,B30)>1,"Yes","No") -> Yes | M30: =IF(H30>15,"yes","no") -> no | N30: =IF(AND(L30="Yes", J30="yes" ),"Yes","No") -> No | O30: =SUMIF('raw data'!B$2:B$501,B30,'raw data'!I$2:I$501) -> 897 | P30: =IF(OR(I30<Visualization!$B$6,I30>Visualization!$B$7),"Outlier","Normal") -> Normal
A31: O10029 | B31: 44975 | C31: C186 | D31: Fashion | E31: P3 | F31: 1 | G31: 499 | I31: 499 | J31: =IF(I31>formulas!$B$5,"yes","no") -> no | K31: =IF(H31>0,"yes","no") -> no | L31: =IF(COUNTIF('raw data'!$B$2:$B$501,B31)>1,"Yes","No") -> Yes | M31: =IF(H31>15,"yes","no") -> no | N31: =IF(AND(L31="Yes", J31="yes" ),"Yes","No") -> No | O31: =SUMIF('raw data'!B$2:B$501,B31,'raw data'!I$2:I$501) -> 668.15 | P31: =IF(OR(I31<Visualization!$B$6,I31>Visualization!$B$7),"Outlier","Normal") -> Outlier
A32: O10030 | B32: 44985 | C32: C180 | D32: Fashion | E32: P6 | F32: 3 | G32: 299 | I32: 897 | J32: =IF(I32>formulas!$B$5,"yes","no") -> no | K32: =IF(H32>0,"yes","no") -> no | L32: =IF(COUNTIF('raw data'!$B$2:$B$501,B32)>1,"Yes","No") -> No | M32: =IF(H32>15,"yes","no") -> no | N32: =IF(AND(L32="Yes", J32="yes" ),"Yes","No") -> No | O32: =SUMIF('raw data'!B$2:B$501,B32,'raw data'!I$2:I$501) -> 897 | P32: =IF(OR(I32<Visualization!$B$6,I32>Visualization!$B$7),"Outlier","Normal") -> Outlier
A33: O10031 | B33: 45096 | C33: C189 | D33: Sports | E33: P5 | F33: 3 | G33: 299 | I33: 897 | J33: =IF(I33>formulas!$B$5,"yes","no") -> no | K33: =IF(H33>0,"yes","no") -> no | L33: =IF(COUNTIF('raw data'!$B$2:$B$501,B33)>1,"Yes","No") -> Yes | M33: =IF(H33>15,"yes","no") -> no | N33: =IF(AND(L33="Yes", J33="yes" ),"Yes","No") -> No | O33: =SUMIF('raw data'!B$2:B$501,B33,'raw data'!I$2:I$501) -> 5689 | P33: =IF(OR(I33<Visualization!$B$6,I33>Visualization!$B$7),"Outlier","Normal") -> Outlier
A34: O10032 | B34: 45114 | C34: C107 | D34: Fashion | E34: P5 | F34: 2 | G34: 1999 | H34: 15 | I34: 3398.3 | J34: =IF(I34>formulas!$B$5,"yes","no") -> yes | K34: =IF(H34>0,"yes","no") -> yes | L34: =IF(COUNTIF('raw data'!$B$2:$B$501,B34)>1,"Yes","No") -> Yes | M34: =IF(H34>15,"yes","no") -> no | N34: =IF(AND(L34="Yes", J34="yes" ),"Yes","No") -> Yes | O34: =SUMIF('raw data'!B$2:B$501,B34,'raw data'!I$2:I$501) -> 6794.9 | P34: =IF(OR(I34<Visualization!$B$6,I34>Visualization!$B$7),"Outlier","Normal") -> Outlier
A35: O10033 | B35: 45197 | C35: C192 | D35: Beauty | E35: P54 | F35: 2 | G35: 1999 | H35: 20 | I35: 3198.4 | J35: =IF(I35>formulas!$B$5,"yes","no") -> yes | K35: =IF(H35>0,"yes","no") -> yes | L35: =IF(COUNTIF('raw data'!$B$2:$B$501,B35)>1,"Yes","No") -> Yes | M35: =IF(H35>15,"yes","no") -> yes | N35: =IF(AND(L35="Yes", J35="yes" ),"Yes","No") -> Yes | O35: =SUMIF('raw data'!B$2:B$501,B35,'raw data'!I$2:I$501) -> 3556.6 | P35: =IF(OR(I35<Visualization!$B$6,I35>Visualization!$B$7),"Outlier","Normal") -> Outlier
A36: O10034 | B36: 45116 | C36: C125 | D36: Fashion | E36: P47 | F36: 3 | G36: 1499 | I36: 4497 | J36: =IF(I36>formulas!$B$5,"yes","no") -> yes | K36: =IF(H36>0,"yes","no") -> no | L36: =IF(COUNTIF('raw data'!$B$2:$B$501,B36)>1,"Yes","No") -> Yes | M36: =IF(H36>15,"yes","no") -> no | N36: =IF(AND(L36="Yes", J36="yes" ),"Yes","No") -> Yes | O36: =SUMIF('raw data'!B$2:B$501,B36,'raw data'!I$2:I$501) -> 6729 | P36: =IF(OR(I36<Visualization!$B$6,I36>Visualization!$B$7),"Outlier","Normal") -> Outlier
A37: O10035 | B37: 45101 | C37: C173 | D37: Sports | E37: P87 | F37: 0 | G37: 299 | H37: 10 | I37: 0 | J37: =IF(I37>formulas!$B$5,"yes","no") -> no | K37: =IF(H37>0,"yes","no") -> yes | L37: =IF(COUNTIF('raw data'!$B$2:$B$501,B37)>1,"Yes","No") -> No | M37: =IF(H37>15,"yes","no") -> no | N37: =IF(AND(L37="Yes", J37="yes" ),"Yes","No") -> No | O37: =SUMIF('raw data'!B$2:B$501,B37,'raw data'!I$2:I$501) -> 0 | P37: =IF(OR(I37<Visualization!$B$6,I37>Visualization!$B$7),"Outlier","Normal") -> Normal
A38: O10036 | B38: 44977 | C38: C189 | D38: Fashion | E38: P49 | F38: 2 | G38: 999 | H38: 10 | I38: 1798.2 | J38: =IF(I38>formulas!$B$5,"yes","no") -> yes | K38: =IF(H38>0,"yes","no") -> yes | L38: =IF(COUNTIF('raw data'!$B$2:$B$501,B38)>1,"Yes","No") -> Yes | M38: =IF(H38>15,"yes","no") -> no | N38: =IF(AND(L38="Yes", J38="yes" ),"Yes","No") -> Yes | O38: =SUMIF('raw data'!B$2:B$501,B38,'raw data'!I$2:I$501) -> 6245.55 | P38: =IF(OR(I38<Visualization!$B$6,I38>Visualization!$B$7),"Outlier","Normal") -> Outlier
A39: O10037 | B39: 45290 | C39: C133 | D39: Beauty | E39: P9 | G39: 199 | J39: =IF(I39>formulas!$B$5,"yes","no") -> no | K39: =IF(H39>0,"yes","no") -> no | L39: =IF(COUNTIF('raw data'!$B$2:$B$501,B39)>1,"Yes","No") -> No | M39: =IF(H39>15,"yes","no") -> no | N39: =IF(AND(L39="Yes", J39="yes" ),"Yes","No") -> No | O39: =SUMIF('raw data'!B$2:B$501,B39,'raw data'!I$2:I$501) -> 0 | P39: =IF(OR(I39<Visualization!$B$6,I39>Visualization!$B$7),"Outlier","Normal") -> Normal
A40: O10038 | B40: 44981 | C40: C106 | D40: Electronics | E40: P99 | F40: 3 | G40: 499 | I40: 1497 | J40: =IF(I40>formulas!$B$5,"yes","no") -> yes | K40: =IF(H40>0,"yes","no") -> no | L40: =IF(COUNTIF('raw data'!$B$2:$B$501,B40)>1,"Yes","No") -> No | M40: =IF(H40>15,"yes","no") -> no | N40: =IF(AND(L40="Yes", J40="yes" ),"Yes","No") -> No | O40: =SUMIF('raw data'!B$2:B$501,B40,'raw data'!I$2:I$501) -> 1497 | P40: =IF(OR(I40<Visualization!$B$6,I40>Visualization!$B$7),"Outlier","Normal") -> Outlier
A41: O10039 | B41: 45170 | C41: C167 | D41: Sports | E41: P20 | F41: 1 | G41: 1999 | H41: 10 | I41: 1799.1 | J41: =IF(I41>formulas!$B$5,"yes","no") -> yes | K41: =IF(H41>0,"yes","no") -> yes | L41: =IF(COUNTIF('raw data'!$B$2:$B$501,B41)>1,"Yes","No") -> No | M41: =IF(H41>15,"yes","no") -> no | N41: =IF(AND(L41="Yes", J41="yes" ),"Yes","No") -> No | O41: =SUMIF('raw data'!B$2:B$501,B41,'raw data'!I$2:I$501) -> 1799.1 | P41: =IF(OR(I41<Visualization!$B$6,I41>Visualization!$B$7),"Outlier","Normal") -> Outlier
A42: O10040 | B42: 45246 | C42: C157 | D42: Electronics | E42: P61 | F42: 2 | G42: 999 | H42: 15 | I42: 1698.3 | J42: =IF(I42>formulas!$B$5,"yes","no") -> yes | K42: =IF(H42>0,"yes","no") -> yes | L42: =IF(COUNTIF('raw data'!$B$2:$B$501,B42)>1,"Yes","No") -> No | M42: =IF(H42>15,"yes","no") -> no | N42: =IF(AND(L42="Yes", J42="yes" ),"Yes","No") -> No | O42: =SUMIF('raw data'!B$2:B$501,B42,'raw data'!I$2:I$501) -> 1698.3 | P42: =IF(OR(I42<Visualization!$B$6,I42>Visualization!$B$7),"Outlier","Normal") -> Outlier
A43: O10041 | B43: 45057 | C43: C174 | D43: Electronics | E43: P35 | F43: 2 | G43: 499 | H43: 0 | I43: 998 | J43: =IF(I43>formulas!$B$5,"yes","no") -> no | K43: =IF(H43>0,"yes","no") -> no | L43: =IF(COUNTIF('raw data'!$B$2:$B$501,B43)>1,"Yes","No") -> Yes | M43: =IF(H43>15,"yes","no") -> no | N43: =IF(AND(L43="Yes", J43="yes" ),"Yes","No") -> No | O43: =SUMIF('raw data'!B$2:B$501,B43,'raw data'!I$2:I$501) -> 2495 | P43: =IF(OR(I43<Visualization!$B$6,I43>Visualization!$B$7),"Outlier","Normal") -> Outlier
A44: O10042 | B44: 45233 | C44: C128 | D44: Electronics | E44: P50 | F44: 2 | G44: 499 | H44: 0 | I44: 998 | J44: =IF(I44>formulas!$B$5,"yes","no") -> no | K44: =IF(H44>0,"yes","no") -> no | L44: =IF(COUNTIF('raw data'!$B$2:$B$501,B44)>1,"Yes","No") -> Yes | M44: =IF(H44>15,"yes","no") -> no | N44: =IF(AND(L44="Yes", J44="yes" ),"Yes","No") -> No | O44: =SUMIF('raw data'!B$2:B$501,B44,'raw data'!I$2:I$501) -> 2997 | P44: =IF(OR(I44<Visualization!$B$6,I44>Visualization!$B$7),"Outlier","Normal") -> Outlier
A45: O10043 | B45: 45061 | C45: C135 | D45: Home | E45: P82 | F45: 1 | G45: 199 | I45: 199 | J45: =IF(I45>formulas!$B$5,"yes","no") -> no | K45: =IF(H45>0,"yes","no") -> no | L45: =IF(COUNTIF('raw data'!$B$2:$B$501,B45)>1,"Yes","No") -> Yes | M45: =IF(H45>15,"yes","no") -> no | N45: =IF(AND(L45="Yes", J45="yes" ),"Yes","No") -> No | O45: =SUMIF('raw data'!B$2:B$501,B45,'raw data'!I$2:I$501) -> 10466.95 | P45: =IF(OR(I45<Visualization!$B$6,I45>Visualization!$B$7),"Outlier","Normal") -> Outlier
A46: O10044 | B46: 44947 | C46: C188 | D46: Home | E46: P62 | F46: 1 | G46: 1499 | H46: 5 | I46: 1424.05 | J46: =IF(I46>formulas!$B$5,"yes","no") -> yes | K46: =IF(H46>0,"yes","no") -> yes | L46: =IF(COUNTIF('raw data'!$B$2:$B$501,B46)>1,"Yes","No") -> Yes | M46: =IF(H46>15,"yes","no") -> no | N46: =IF(AND(L46="Yes", J46="yes" ),"Yes","No") -> Yes | O46: =SUMIF('raw data'!B$2:B$501,B46,'raw data'!I$2:I$501) -> 1782.25 | P46: =IF(OR(I46<Visualization!$B$6,I46>Visualization!$B$7),"Outlier","Normal") -> Outlier
A47: O10045 | B47: 45255 | C47: C120 | D47: Electronics | E47: P17 | F47: 1 | G47: 299 | I47: 299 | J47: =IF(I47>formulas!$B$5,"yes","no") -> no | K47: =IF(H47>0,"yes","no") -> no | L47: =IF(COUNTIF('raw data'!$B$2:$B$501,B47)>1,"Yes","No") -> No | M47: =IF(H47>15,"yes","no") -> no | N47: =IF(AND(L47="Yes", J47="yes" ),"Yes","No") -> No | O47: =SUMIF('raw data'!B$2:B$501,B47,'raw data'!I$2:I$501) -> 299 | P47: =IF(OR(I47<Visualization!$B$6,I47>Visualization!$B$7),"Outlier","Normal") -> Outlier
A48: O10046 | B48: 45093 | C48: C135 | D48: Sports | E48: P88 | F48: 5 | G48: 199 | I48: 995 | J48: =IF(I48>formulas!$B$5,"yes","no") -> no | K48: =IF(H48>0,"yes","no") -> no | L48: =IF(COUNTIF('raw data'!$B$2:$B$501,B48)>1,"Yes","No") -> No | M48: =IF(H48>15,"yes","no") -> no | N48: =IF(AND(L48="Yes", J48="yes" ),"Yes","No") -> No | O48: =SUMIF('raw data'!B$2:B$501,B48,'raw data'!I$2:I$501) -> 995 | P48: =IF(OR(I48<Visualization!$B$6,I48>Visualization!$B$7),"Outlier","Normal") -> Outlier
A49: O10047 | B49: 45200 | C49: C109 | D49: Beauty | E49: P3 | F49: 3 | G49: 999 | H49: 0 | I49: 2997 | J49: =IF(I49>formulas!$B$5,"yes","no") -> yes | K49: =IF(H49>0,"yes","no") -> no | L49: =IF(COUNTIF('raw data'!$B$2:$B$501,B49)>1,"Yes","No") -> No | M49: =IF(H49>15,"yes","no") -> no | N49: =IF(AND(L49="Yes", J49="yes" ),"Yes","No") -> No | O49: =SUMIF('raw data'!B$2:B$501,B49,'raw data'!I$2:I$501) -> 2997 | P49: =IF(OR(I49<Visualization!$B$6,I49>Visualization!$B$7),"Outlier","Normal") -> Outlier
A50: O10048 | B50: 45015 | C50: C172 | D50: Beauty | E50: P32 | F50: 1 | G50: 1499 | H50: 10 | I50: 1349.1 | J50: =IF(I50>formulas!$B$5,"yes","no") -> no | K50: =IF(H50>0,"yes","no") -> yes | L50: =IF(COUNTIF('raw data'!$B$2:$B$501,B50)>1,"Yes","No") -> Yes | M50: =IF(H50>15,"yes","no") -> no | N50: =IF(AND(L50="Yes", J50="yes" ),"Yes","No") -> No | O50: =SUMIF('raw data'!B$2:B$501,B50,'raw data'!I$2:I$501) -> 1748.3 | P50: =IF(OR(I50<Visualization!$B$6,I50>Visualization!$B$7),"Outlier","Normal") -> Outlier
A51: O10049 | B51: 45242 | C51: C123 | D51: Fashion | E51: P99 | F51: 1 | G51: 999 | I51: 999 | J51: =IF(I51>formulas!$B$5,"yes","no") -> no | K51: =IF(H51>0,"yes","no") -> no | L51: =IF(COUNTIF('raw data'!$B$2:$B$501,B51)>1,"Yes","No") -> Yes | M51: =IF(H51>15,"yes","no") -> no | N51: =IF(AND(L51="Yes", J51="yes" ),"Yes","No") -> No | O51: =SUMIF('raw data'!B$2:B$501,B51,'raw data'!I$2:I$501) -> 1397 | P51: =IF(OR(I51<Visualization!$B$6,I51>Visualization!$B$7),"Outlier","Normal") -> Outlier
A52: O10050 | B52: 44940 | C52: C163 | D52: Sports | E52: P13 | F52: 3 | G52: 1499 | H52: 10 | I52: 4047.3 | J52: =IF(I52>formulas!$B$5,"yes","no") -> yes | K52: =IF(H52>0,"yes","no") -> yes | L52: =IF(COUNTIF('raw data'!$B$2:$B$501,B52)>1,"Yes","No") -> No | M52: =IF(H52>15,"yes","no") -> no | N52: =IF(AND(L52="Yes", J52="yes" ),"Yes","No") -> No | O52: =SUMIF('raw data'!B$2:B$501,B52,'raw data'!I$2:I$501) -> 4047.3 | P52: =IF(OR(I52<Visualization!$B$6,I52>Visualization!$B$7),"Outlier","Normal") -> Outlier
A53: O10051 | B53: 45168 | C53: C198 | D53: Home | E53: P89 | F53: 1 | G53: 1999 | H53: 10 | I53: 1799.1 | J53: =IF(I53>formulas!$B$5,"yes","no") -> yes | K53: =IF(H53>0,"yes","no") -> yes | L53: =IF(COUNTIF('raw data'!$B$2:$B$501,B53)>1,"Yes","No") -> No | M53: =IF(H53>15,"yes","no") -> no | N53: =IF(AND(L53="Yes", J53="yes" ),"Yes","No") -> No | O53: =SUMIF('raw data'!B$2:B$501,B53,'raw data'!I$2:I$501) -> 1799.1 | P53: =IF(OR(I53<Visualization!$B$6,I53>Visualization!$B$7),"Outlier","Normal") -> Outlier
A54: O10052 | B54: 45191 | C54: C148 | D54: Electronics | E54: P73 | F54: 1 | G54: 999 | H54: 5 | I54: 949.05 | J54: =IF(I54>formulas!$B$5,"yes","no") -> no | K54: =IF(H54>0,"yes","no") -> yes | L54: =IF(COUNTIF('raw data'!$B$2:$B$501,B54)>1,"Yes","No") -> No | M54: =IF(H54>15,"yes","no") -> no | N54: =IF(AND(L54="Yes", J54="yes" ),"Yes","No") -> No | O54: =SUMIF('raw data'!B$2:B$501,B54,'raw data'!I$2:I$501) -> 949.05 | P54: =IF(OR(I54<Visualization!$B$6,I54>Visualization!$B$7),"Outlier","Normal") -> Outlier
A55: O10053 | B55: 45272 | C55: C198 | D55: Fashion | E55: P68 | G55: 199 | H55: 10 | J55: =IF(I55>formulas!$B$5,"yes","no") -> no | K55: =IF(H55>0,"yes","no") -> yes | L55: =IF(COUNTIF('raw data'!$B$2:$B$501,B55)>1,"Yes","No") -> Yes | M55: =IF(H55>15,"yes","no") -> no | N55: =IF(AND(L55="Yes", J55="yes" ),"Yes","No") -> No | O55: =SUMIF('raw data'!B$2:B$501,B55,'raw data'!I$2:I$501) -> 3653.7 | P55: =IF(OR(I55<Visualization!$B$6,I55>Visualization!$B$7),"Outlier","Normal") -> Normal
A56: O10054 | B56: 44979 | C56: C135 | D56: Beauty | E56: P14 | F56: 1 | G56: 1499 | H56: 0 | I56: 1499 | J56: =IF(I56>formulas!$B$5,"yes","no") -> yes | K56: =IF(H56>0,"yes","no") -> no | L56: =IF(COUNTIF('raw data'!$B$2:$B$501,B56)>1,"Yes","No") -> Yes | M56: =IF(H56>15,"yes","no") -> no | N56: =IF(AND(L56="Yes", J56="yes" ),"Yes","No") -> Yes | O56: =SUMIF('raw data'!B$2:B$501,B56,'raw data'!I$2:I$501) -> 3531.3 | P56: =IF(OR(I56<Visualization!$B$6,I56>Visualization!$B$7),"Outlier","Normal") -> Outlier
A57: O10055 | B57: 45266 | C57: C181 | D57: Home | E57: P98 | F57: 3 | G57: 1499 | H57: 15 | I57: 3822.45 | J57: =IF(I57>formulas!$B$5,"yes","no") -> yes | K57: =IF(H57>0,"yes","no") -> yes | L57: =IF(COUNTIF('raw data'!$B$2:$B$501,B57)>1,"Yes","No") -> Yes | M57: =IF(H57>15,"yes","no") -> no | N57: =IF(AND(L57="Yes", J57="yes" ),"Yes","No") -> Yes | O57: =SUMIF('raw data'!B$2:B$501,B57,'raw data'!I$2:I$501) -> 11363.95 | P57: =IF(OR(I57<Visualization!$B$6,I57>Visualization!$B$7),"Outlier","Normal") -> Outlier
A58: O10056 | B58: 45018 | C58: C195 | D58: Home | E58: P11 | G58: 499 | H58: 15 | J58: =IF(I58>formulas!$B$5,"yes","no") -> no | K58: =IF(H58>0,"yes","no") -> yes | L58: =IF(COUNTIF('raw data'!$B$2:$B$501,B58)>1,"Yes","No") -> Yes | M58: =IF(H58>15,"yes","no") -> no | N58: =IF(AND(L58="Yes", J58="yes" ),"Yes","No") -> No | O58: =SUMIF('raw data'!B$2:B$501,B58,'raw data'!I$2:I$501) -> 2892.6 | P58: =IF(OR(I58<Visualization!$B$6,I58>Visualization!$B$7),"Outlier","Normal") -> Normal
A59: O10057 | B59: 45190 | C59: C123 | D59: Electronics | E59: P56 | F59: 2 | G59: 499 | H59: 20 | I59: 798.4 | J59: =IF(I59>formulas!$B$5,"yes","no") -> no | K59: =IF(H59>0,"yes","no") -> yes | L59: =IF(COUNTIF('raw data'!$B$2:$B$501,B59)>1,"Yes","No") -> Yes | M59: =IF(H59>15,"yes","no") -> yes | N59: =IF(AND(L59="Yes", J59="yes" ),"Yes","No") -> No | O59: =SUMIF('raw data'!B$2:B$501,B59,'raw data'!I$2:I$501) -> 10189.2 | P59: =IF(OR(I59<Visualization!$B$6,I59>Visualization!$B$7),"Outlier","Normal") -> Outlier
A60: O10058 | B60: 44961 | C60: C122 | D60: Beauty | E60: P67 | F60: 0 | J60: =IF(I60>formulas!$B$5,"yes","no") -> no | K60: =IF(H60>0,"yes","no") -> no | L60: =IF(COUNTIF('raw data'!$B$2:$B$501,B60)>1,"Yes","No") -> Yes | M60: =IF(H60>15,"yes","no") -> no | N60: =IF(AND(L60="Yes", J60="yes" ),"Yes","No") -> No | O60: =SUMIF('raw data'!B$2:B$501,B60,'raw data'!I$2:I$501) -> 4197.4 | P60: =IF(OR(I60<Visualization!$B$6,I60>Visualization!$B$7),"Outlier","Normal") -> Normal
A61: O10059 | B61: 45132 | C61: C161 | D61: Sports | E61: P92 | F61: 1 | G61: 999 | H61: 0 | I61: 999 | J61: =IF(I61>formulas!$B$5,"yes","no") -> no | K61: =IF(H61>0,"yes","no") -> no | L61: =IF(COUNTIF('raw data'!$B$2:$B$501,B61)>1,"Yes","No") -> No | M61: =IF(H61>15,"yes","no") -> no | N61: =IF(AND(L61="Yes", J61="yes" ),"Yes","No") -> No | O61: =SUMIF('raw data'!B$2:B$501,B61,'raw data'!I$2:I$501) -> 999 | P61: =IF(OR(I61<Visualization!$B$6,I61>Visualization!$B$7),"Outlier","Normal") -> Outlier
A62: O10060 | B62: 45007 | C62: C195 | D62: Home | E62: P29 | F62: 4 | G62: 499 | H62: 10 | I62: 1796.4 | J62: =IF(I62>formulas!$B$5,"yes","no") -> yes | K62: =IF(H62>0,"yes","no") -> yes | L62: =IF(COUNTIF('raw data'!$B$2:$B$501,B62)>1,"Yes","No") -> Yes | M62: =IF(H62>15,"yes","no") -> no | N62: =IF(AND(L62="Yes", J62="yes" ),"Yes","No") -> Yes | O62: =SUMIF('raw data'!B$2:B$501,B62,'raw data'!I$2:I$501) -> 4393.8 | P62: =IF(OR(I62<Visualization!$B$6,I62>Visualization!$B$7),"Outlier","Normal") -> Outlier
A63: O10061 | B63: 44976 | C63: C136 | D63: Electronics | E63: P9 | F63: 4 | H63: 15 | J63: =IF(I63>formulas!$B$5,"yes","no") -> no | K63: =IF(H63>0,"yes","no") -> yes | L63: =IF(COUNTIF('raw data'!$B$2:$B$501,B63)>1,"Yes","No") -> No | M63: =IF(H63>15,"yes","no") -> no | N63: =IF(AND(L63="Yes", J63="yes" ),"Yes","No") -> No | O63: =SUMIF('raw data'!B$2:B$501,B63,'raw data'!I$2:I$501) -> 0 | P63: =IF(OR(I63<Visualization!$B$6,I63>Visualization!$B$7),"Outlier","Normal") -> Normal
A64: O10062 | B64: 45286 | C64: C111 | D64: Sports | E64: P67 | F64: 4 | G64: 1999 | H64: 0 | I64: 7996 | J64: =IF(I64>formulas!$B$5,"yes","no") -> yes | K64: =IF(H64>0,"yes","no") -> no | L64: =IF(COUNTIF('raw data'!$B$2:$B$501,B64)>1,"Yes","No") -> Yes | M64: =IF(H64>15,"yes","no") -> no | N64: =IF(AND(L64="Yes", J64="yes" ),"Yes","No") -> Yes | O64: =SUMIF('raw data'!B$2:B$501,B64,'raw data'!I$2:I$501) -> 11794.1 | P64: =IF(OR(I64<Visualization!$B$6,I64>Visualization!$B$7),"Outlier","Normal") -> Outlier
A65: O10063 | B65: 44928 | C65: C154 | D65: Beauty | E65: P25 | F65: 1 | G65: 1999 | H65: 15 | I65: 1699.15 | J65: =IF(I65>formulas!$B$5,"yes","no") -> yes | K65: =IF(H65>0,"yes","no") -> yes | L65: =IF(COUNTIF('raw data'!$B$2:$B$501,B65)>1,"Yes","No") -> Yes | M65: =IF(H65>15,"yes","no") -> no | N65: =IF(AND(L65="Yes", J65="yes" ),"Yes","No") -> Yes | O65: =SUMIF('raw data'!B$2:B$501,B65,'raw data'!I$2:I$501) -> 1699.15 | P65: =IF(OR(I65<Visualization!$B$6,I65>Visualization!$B$7),"Outlier","Normal") -> Outlier
A66: O10064 | B66: 44980 | C66: C112 | D66: Home | E66: P98 | F66: 4 | G66: 499 | H66: 10 | I66: 1796.4 | J66: =IF(I66>formulas!$B$5,"yes","no") -> yes | K66: =IF(H66>0,"yes","no") -> yes | L66: =IF(COUNTIF('raw data'!$B$2:$B$501,B66)>1,"Yes","No") -> Yes | M66: =IF(H66>15,"yes","no") -> no | N66: =IF(AND(L66="Yes", J66="yes" ),"Yes","No") -> Yes | O66: =SUMIF('raw data'!B$2:B$501,B66,'raw data'!I$2:I$501) -> 6687.6 | P66: =IF(OR(I66<Visualization!$B$6,I66>Visualization!$B$7),"Outlier","Normal") -> Outlier
A67: O10065 | B67: 45032 | C67: C122 | D67: Sports | E67: P76 | F67: 5 | G67: 999 | H67: 15 | I67: 4245.75 | J67: =IF(I67>formulas!$B$5,"yes","no") -> yes | K67: =IF(H67>0,"yes","no") -> yes | L67: =IF(COUNTIF('raw data'!$B$2:$B$501,B67)>1,"Yes","No") -> Yes | M67: =IF(H67>15,"yes","no") -> no | N67: =IF(AND(L67="Yes", J67="yes" ),"Yes","No") -> Yes | O67: =SUMIF('raw data'!B$2:B$501,B67,'raw data'!I$2:I$501) -> 8068.2 | P67: =IF(OR(I67<Visualization!$B$6,I67>Visualization!$B$7),"Outlier","Normal") -> Outlier
A68: O10066 | B68: 45186 | C68: C188 | D68: Sports | E68: P42 | F68: 3 | G68: 1499 | I68: 4497 | J68: =IF(I68>formulas!$B$5,"yes","no") -> yes | K68: =IF(H68>0,"yes","no") -> no | L68: =IF(COUNTIF('raw data'!$B$2:$B$501,B68)>1,"Yes","No") -> No | M68: =IF(H68>15,"yes","no") -> no | N68: =IF(AND(L68="Yes", J68="yes" ),"Yes","No") -> No | O68: =SUMIF('raw data'!B$2:B$501,B68,'raw data'!I$2:I$501) -> 4497 | P68: =IF(OR(I68<Visualization!$B$6,I68>Visualization!$B$7),"Outlier","Normal") -> Outlier
A69: O10067 | B69: 45236 | C69: C198 | D69: Sports | E69: P9 | F69: 5 | G69: 299 | I69: 1495 | J69: =IF(I69>formulas!$B$5,"yes","no") -> yes | K69: =IF(H69>0,"yes","no") -> no | L69: =IF(COUNTIF('raw data'!$B$2:$B$501,B69)>1,"Yes","No") -> Yes | M69: =IF(H69>15,"yes","no") -> no | N69: =IF(AND(L69="Yes", J69="yes" ),"Yes","No") -> Yes | O69: =SUMIF('raw data'!B$2:B$501,B69,'raw data'!I$2:I$501) -> 1813.4 | P69: =IF(OR(I69<Visualization!$B$6,I69>Visualization!$B$7),"Outlier","Normal") -> Outlier
A70: O10068 | B70: 45117 | C70: C129 | D70: Home | E70: P79 | F70: 4 | G70: 999 | H70: 20 | I70: 3196.8 | J70: =IF(I70>formulas!$B$5,"yes","no") -> yes | K70: =IF(H70>0,"yes","no") -> yes | L70: =IF(COUNTIF('raw data'!$B$2:$B$501,B70)>1,"Yes","No") -> Yes | M70: =IF(H70>15,"yes","no") -> yes | N70: =IF(AND(L70="Yes", J70="yes" ),"Yes","No") -> Yes | O70: =SUMIF('raw data'!B$2:B$501,B70,'raw data'!I$2:I$501) -> 3196.8 | P70: =IF(OR(I70<Visualization!$B$6,I70>Visualization!$B$7),"Outlier","Normal") -> Outlier
A71: O10069 | B71: 45144 | C71: C116 | D71: Home | E71: P40 | F71: 3 | G71: 199 | H71: 20 | I71: 477.6 | J71: =IF(I71>formulas!$B$5,"yes","no") -> no | K71: =IF(H71>0,"yes","no") -> yes | L71: =IF(COUNTIF('raw data'!$B$2:$B$501,B71)>1,"Yes","No") -> Yes | M71: =IF(H71>15,"yes","no") -> yes | N71: =IF(AND(L71="Yes", J71="yes" ),"Yes","No") -> No | O71: =SUMIF('raw data'!B$2:B$501,B71,'raw data'!I$2:I$501) -> 6171.7 | P71: =IF(OR(I71<Visualization!$B$6,I71>Visualization!$B$7),"Outlier","Normal") -> Outlier
A72: O10070 | B72: 44970 | C72: C161 | D72: Fashion | E72: P25 | F72: 3 | G72: 1999 | H72: 15 | I72: 5097.45 | J72: =IF(I72>formulas!$B$5,"yes","no") -> yes | K72: =IF(H72>0,"yes","no") -> yes | L72: =IF(COUNTIF('raw data'!$B$2:$B$501,B72)>1,"Yes","No") -> Yes | M72: =IF(H72>15,"yes","no") -> no | N72: =IF(AND(L72="Yes", J72="yes" ),"Yes","No") -> Yes | O72: =SUMIF('raw data'!B$2:B$501,B72,'raw data'!I$2:I$501) -> 5995.65 | P72: =IF(OR(I72<Visualization!$B$6,I72>Visualization!$B$7),"Outlier","Normal") -> Outlier
A73: O10071 | B73: 45088 | C73: C183 | D73: Beauty | E73: P5 | F73: 2 | G73: 499 | H73: 0 | I73: 998 | J73: =IF(I73>formulas!$B$5,"yes","no") -> no | K73: =IF(H73>0,"yes","no") -> no | L73: =IF(COUNTIF('raw data'!$B$2:$B$501,B73)>1,"Yes","No") -> No | M73: =IF(H73>15,"yes","no") -> no | N73: =IF(AND(L73="Yes", J73="yes" ),"Yes","No") -> No | O73: =SUMIF('raw data'!B$2:B$501,B73,'raw data'!I$2:I$501) -> 998 | P73: =IF(OR(I73<Visualization!$B$6,I73>Visualization!$B$7),"Outlier","Normal") -> Outlier
A74: O10072 | B74: 45128 | C74: C188 | D74: Electronics | E74: P11 | F74: 1 | G74: 499 | I74: 499 | J74: =IF(I74>formulas!$B$5,"yes","no") -> no | K74: =IF(H74>0,"yes","no") -> no | L74: =IF(COUNTIF('raw data'!$B$2:$B$501,B74)>1,"Yes","No") -> No | M74: =IF(H74>15,"yes","no") -> no | N74: =IF(AND(L74="Yes", J74="yes" ),"Yes","No") -> No | O74: =SUMIF('raw data'!B$2:B$501,B74,'raw data'!I$2:I$501) -> 499 | P74: =IF(OR(I74<Visualization!$B$6,I74>Visualization!$B$7),"Outlier","Normal") -> Outlier
A75: O10073 | B75: 45196 | C75: C185 | D75: Sports | E75: P59 | F75: 3 | G75: 1499 | H75: 0 | I75: 4497 | J75: =IF(I75>formulas!$B$5,"yes","no") -> yes | K75: =IF(H75>0,"yes","no") -> no | L75: =IF(COUNTIF('raw data'!$B$2:$B$501,B75)>1,"Yes","No") -> No | M75: =IF(H75>15,"yes","no") -> no | N75: =IF(AND(L75="Yes", J75="yes" ),"Yes","No") -> No | O75: =SUMIF('raw data'!B$2:B$501,B75,'raw data'!I$2:I$501) -> 4497 | P75: =IF(OR(I75<Visualization!$B$6,I75>Visualization!$B$7),"Outlier","Normal") -> Outlier
A76: O10074 | B76: 45277 | C76: C112 | D76: Fashion | E76: P98 | F76: 2 | G76: 199 | H76: 0 | I76: 398 | J76: =IF(I76>formulas!$B$5,"yes","no") -> no | K76: =IF(H76>0,"yes","no") -> no | L76: =IF(COUNTIF('raw data'!$B$2:$B$501,B76)>1,"Yes","No") -> No | M76: =IF(H76>15,"yes","no") -> no | N76: =IF(AND(L76="Yes", J76="yes" ),"Yes","No") -> No | O76: =SUMIF('raw data'!B$2:B$501,B76,'raw data'!I$2:I$501) -> 398 | P76: =IF(OR(I76<Visualization!$B$6,I76>Visualization!$B$7),"Outlier","Normal") -> Outlier
A77: O10075 | B77: 45230 | C77: C158 | D77: Electronics | E77: P88 | F77: 4 | G77: 1499 | H77: 15 | I77: 5096.6 | J77: =IF(I77>formulas!$B$5,"yes","no") -> yes | K77: =IF(H77>0,"yes","no") -> yes | L77: =IF(COUNTIF('raw data'!$B$2:$B$501,B77)>1,"Yes","No") -> Yes | M77: =IF(H77>15,"yes","no") -> no | N77: =IF(AND(L77="Yes", J77="yes" ),"Yes","No") -> Yes | O77: =SUMIF('raw data'!B$2:B$501,B77,'raw data'!I$2:I$501) -> 14386.9 | P77: =IF(OR(I77<Visualization!$B$6,I77>Visualization!$B$7),"Outlier","Normal") -> Outlier
A78: O10076 | B78: 45197 | C78: C118 | D78: Fashion | E78: P79 | G78: 199 | H78: 0 | J78: =IF(I78>formulas!$B$5,"yes","no") -> no | K78: =IF(H78>0,"yes","no") -> no | L78: =IF(COUNTIF('raw data'!$B$2:$B$501,B78)>1,"Yes","No") -> Yes | M78: =IF(H78>15,"yes","no") -> no | N78: =IF(AND(L78="Yes", J78="yes" ),"Yes","No") -> No | O78: =SUMIF('raw data'!B$2:B$501,B78,'raw data'!I$2:I$501) -> 3556.6 | P78: =IF(OR(I78<Visualization!$B$6,I78>Visualization!$B$7),"Outlier","Normal") -> Normal
A79: O10077 | B79: 45141 | C79: C148 | D79: Home | E79: P38 | F79: 4 | G79: 299 | I79: 1196 | J79: =IF(I79>formulas!$B$5,"yes","no") -> no | K79: =IF(H79>0,"yes","no") -> no | L79: =IF(COUNTIF('raw data'!$B$2:$B$501,B79)>1,"Yes","No") -> Yes | M79: =IF(H79>15,"yes","no") -> no | N79: =IF(AND(L79="Yes", J79="yes" ),"Yes","No") -> No | O79: =SUMIF('raw data'!B$2:B$501,B79,'raw data'!I$2:I$501) -> 4252.4 | P79: =IF(OR(I79<Visualization!$B$6,I79>Visualization!$B$7),"Outlier","Normal") -> Outlier
A80: O10078 | B80: 45178 | C80: C199 | D80: Sports | E80: P72 | F80: 1 | G80: 1999 | H80: 10 | I80: 1799.1 | J80: =IF(I80>formulas!$B$5,"yes","no") -> yes | K80: =IF(H80>0,"yes","no") -> yes | L80: =IF(COUNTIF('raw data'!$B$2:$B$501,B80)>1,"Yes","No") -> Yes | M80: =IF(H80>15,"yes","no") -> no | N80: =IF(AND(L80="Yes", J80="yes" ),"Yes","No") -> Yes | O80: =SUMIF('raw data'!B$2:B$501,B80,'raw data'!I$2:I$501) -> 3694.7 | P80: =IF(OR(I80<Visualization!$B$6,I80>Visualization!$B$7),"Outlier","Normal") -> Outlier
A81: O10079 | B81: 45116 | C81: C111 | D81: Electronics | E81: P5 | F81: 1 | G81: 499 | H81: 20 | I81: 399.2 | J81: =IF(I81>formulas!$B$5,"yes","no") -> no | K81: =IF(H81>0,"yes","no") -> yes | L81: =IF(COUNTIF('raw data'!$B$2:$B$501,B81)>1,"Yes","No") -> Yes | M81: =IF(H81>15,"yes","no") -> yes | N81: =IF(AND(L81="Yes", J81="yes" ),"Yes","No") -> No | O81: =SUMIF('raw data'!B$2:B$501,B81,'raw data'!I$2:I$501) -> 6729 | P81: =IF(OR(I81<Visualization!$B$6,I81>Visualization!$B$7),"Outlier","Normal") -> Outlier
A82: O10080 | B82: 45222 | C82: C160 | D82: Electronics | E82: P48 | F82: 1 | G82: 499 | H82: 10 | I82: 449.1 | J82: =IF(I82>formulas!$B$5,"yes","no") -> no | K82: =IF(H82>0,"yes","no") -> yes | L82: =IF(COUNTIF('raw data'!$B$2:$B$501,B82)>1,"Yes","No") -> No | M82: =IF(H82>15,"yes","no") -> no | N82: =IF(AND(L82="Yes", J82="yes" ),"Yes","No") -> No | O82: =SUMIF('raw data'!B$2:B$501,B82,'raw data'!I$2:I$501) -> 449.1 | P82: =IF(OR(I82<Visualization!$B$6,I82>Visualization!$B$7),"Outlier","Normal") -> Outlier
A83: O10081 | B83: 45139 | C83: C118 | D83: Electronics | E83: P90 | F83: 3 | G83: 299 | H83: 0 | I83: 897 | J83: =IF(I83>formulas!$B$5,"yes","no") -> no | K83: =IF(H83>0,"yes","no") -> no | L83: =IF(COUNTIF('raw data'!$B$2:$B$501,B83)>1,"Yes","No") -> No | M83: =IF(H83>15,"yes","no") -> no | N83: =IF(AND(L83="Yes", J83="yes" ),"Yes","No") -> No | O83: =SUMIF('raw data'!B$2:B$501,B83,'raw data'!I$2:I$501) -> 897 | P83: =IF(OR(I83<Visualization!$B$6,I83>Visualization!$B$7),"Outlier","Normal") -> Outlier
A84: O10082 | B84: 45134 | C84: C175 | D84: Electronics | E84: P18 | F84: 4 | H84: 10 | J84: =IF(I84>formulas!$B$5,"yes","no") -> no | K84: =IF(H84>0,"yes","no") -> yes | L84: =IF(COUNTIF('raw data'!$B$2:$B$501,B84)>1,"Yes","No") -> Yes | M84: =IF(H84>15,"yes","no") -> no | N84: =IF(AND(L84="Yes", J84="yes" ),"Yes","No") -> No | O84: =SUMIF('raw data'!B$2:B$501,B84,'raw data'!I$2:I$501) -> 1225.9 | P84: =IF(OR(I84<Visualization!$B$6,I84>Visualization!$B$7),"Outlier","Normal") -> Normal
A85: O10083 | B85: 45163 | C85: C108 | D85: Electronics | E85: P70 | F85: 5 | G85: 1999 | I85: 9995 | J85: =IF(I85>formulas!$B$5,"yes","no") -> yes | K85: =IF(H85>0,"yes","no") -> no | L85: =IF(COUNTIF('raw data'!$B$2:$B$501,B85)>1,"Yes","No") -> Yes | M85: =IF(H85>15,"yes","no") -> no | N85: =IF(AND(L85="Yes", J85="yes" ),"Yes","No") -> Yes | O85: =SUMIF('raw data'!B$2:B$501,B85,'raw data'!I$2:I$501) -> 17212.35 | P85: =IF(OR(I85<Visualization!$B$6,I85>Visualization!$B$7),"Outlier","Normal") -> Outlier
A86: O10084 | B86: 45264 | C86: C170 | D86: Fashion | E86: P37 | F86: 2 | G86: 1499 | I86: 2998 | J86: =IF(I86>formulas!$B$5,"yes","no") -> yes | K86: =IF(H86>0,"yes","no") -> no | L86: =IF(COUNTIF('raw data'!$B$2:$B$501,B86)>1,"Yes","No") -> Yes | M86: =IF(H86>15,"yes","no") -> no | N86: =IF(AND(L86="Yes", J86="yes" ),"Yes","No") -> Yes | O86: =SUMIF('raw data'!B$2:B$501,B86,'raw data'!I$2:I$501) -> 3805.3 | P86: =IF(OR(I86<Visualization!$B$6,I86>Visualization!$B$7),"Outlier","Normal") -> Outlier
A87: O10085 | B87: 44979 | C87: C127 | D87: Sports | E87: P60 | F87: 5 | G87: 299 | H87: 0 | I87: 1495 | J87: =IF(I87>formulas!$B$5,"yes","no") -> yes | K87: =IF(H87>0,"yes","no") -> no | L87: =IF(COUNTIF('raw data'!$B$2:$B$501,B87)>1,"Yes","No") -> Yes | M87: =IF(H87>15,"yes","no") -> no | N87: =IF(AND(L87="Yes", J87="yes" ),"Yes","No") -> Yes | O87: =SUMIF('raw data'!B$2:B$501,B87,'raw data'!I$2:I$501) -> 3531.3 | P87: =IF(OR(I87<Visualization!$B$6,I87>Visualization!$B$7),"Outlier","Normal") -> Outlier
A88: O10086 | B88: 45206 | C88: C177 | D88: Home | E88: P48 | F88: 4 | G88: 1499 | H88: 15 | I88: 5096.6 | J88: =IF(I88>formulas!$B$5,"yes","no") -> yes | K88: =IF(H88>0,"yes","no") -> yes | L88: =IF(COUNTIF('raw data'!$B$2:$B$501,B88)>1,"Yes","No") -> Yes | M88: =IF(H88>15,"yes","no") -> no | N88: =IF(AND(L88="Yes", J88="yes" ),"Yes","No") -> Yes | O88: =SUMIF('raw data'!B$2:B$501,B88,'raw data'!I$2:I$501) -> 8893.7 | P88: =IF(OR(I88<Visualization!$B$6,I88>Visualization!$B$7),"Outlier","Normal") -> Outlier
A89: O10087 | B89: 45143 | C89: C194 | D89: Home | E89: P77 | F89: 2 | G89: 999 | H89: 10 | I89: 1798.2 | J89: =IF(I89>formulas!$B$5,"yes","no") -> yes | K89: =IF(H89>0,"yes","no") -> yes | L89: =IF(COUNTIF('raw data'!$B$2:$B$501,B89)>1,"Yes","No") -> No | M89: =IF(H89>15,"yes","no") -> no | N89: =IF(AND(L89="Yes", J89="yes" ),"Yes","No") -> No | O89: =SUMIF('raw data'!B$2:B$501,B89,'raw data'!I$2:I$501) -> 1798.2 | P89: =IF(OR(I89<Visualization!$B$6,I89>Visualization!$B$7),"Outlier","Normal") -> Outlier
A90: O10088 | B90: 45178 | C90: C151 | D90: Home | E90: P28 | F90: 4 | G90: 499 | H90: 15 | I90: 1696.6 | J90: =IF(I90>formulas!$B$5,"yes","no") -> yes | K90: =IF(H90>0,"yes","no") -> yes | L90: =IF(COUNTIF('raw data'!$B$2:$B$501,B90)>1,"Yes","No") -> Yes | M90: =IF(H90>15,"yes","no") -> no | N90: =IF(AND(L90="Yes", J90="yes" ),"Yes","No") -> Yes | O90: =SUMIF('raw data'!B$2:B$501,B90,'raw data'!I$2:I$501) -> 3694.7 | P90: =IF(OR(I90<Visualization!$B$6,I90>Visualization!$B$7),"Outlier","Normal") -> Outlier
A91: O10089 | B91: 45114 | C91: C182 | D91: Home | E91: P69 | F91: 2 | G91: 1499 | H91: 15 | I91: 2548.3 | J91: =IF(I91>formulas!$B$5,"yes","no") -> yes | K91: =IF(H91>0,"yes","no") -> yes | L91: =IF(COUNTIF('raw data'!$B$2:$B$501,B91)>1,"Yes","No") -> Yes | M91: =IF(H91>15,"yes","no") -> no | N91: =IF(AND(L91="Yes", J91="yes" ),"Yes","No") -> Yes | O91: =SUMIF('raw data'!B$2:B$501,B91,'raw data'!I$2:I$501) -> 6794.9 | P91: =IF(OR(I91<Visualization!$B$6,I91>Visualization!$B$7),"Outlier","Normal") -> Outlier
A92: O10090 | B92: 44967 | C92: C115 | D92: Fashion | E92: P77 | F92: 1 | G92: 199 | H92: 5 | I92: 189.05 | J92: =IF(I92>formulas!$B$5,"yes","no") -> no | K92: =IF(H92>0,"yes","no") -> yes | L92: =IF(COUNTIF('raw data'!$B$2:$B$501,B92)>1,"Yes","No") -> Yes | M92: =IF(H92>15,"yes","no") -> no | N92: =IF(AND(L92="Yes", J92="yes" ),"Yes","No") -> No | O92: =SUMIF('raw data'!B$2:B$501,B92,'raw data'!I$2:I$501) -> 189.05 | P92: =IF(OR(I92<Visualization!$B$6,I92>Visualization!$B$7),"Outlier","Normal") -> Outlier
A93: O10091 | B93: 45083 | C93: C168 | D93: Beauty | E93: P81 | F93: 3 | G93: 1499 | H93: 0 | I93: 4497 | J93: =IF(I93>formulas!$B$5,"yes","no") -> yes | K93: =IF(H93>0,"yes","no") -> no | L93: =IF(COUNTIF('raw data'!$B$2:$B$501,B93)>1,"Yes","No") -> No | M93: =IF(H93>15,"yes","no") -> no | N93: =IF(AND(L93="Yes", J93="yes" ),"Yes","No") -> No | O93: =SUMIF('raw data'!B$2:B$501,B93,'raw data'!I$2:I$501) -> 4497 | P93: =IF(OR(I93<Visualization!$B$6,I93>Visualization!$B$7),"Outlier","Normal") -> Outlier
A94: O10092 | B94: 44941 | C94: C198 | D94: Sports | E94: P40 | F94: 2 | G94: 999 | H94: 20 | I94: 1598.4 | J94: =IF(I94>formulas!$B$5,"yes","no") -> yes | K94: =IF(H94>0,"yes","no") -> yes | L94: =IF(COUNTIF('raw data'!$B$2:$B$501,B94)>1,"Yes","No") -> Yes | M94: =IF(H94>15,"yes","no") -> yes | N94: =IF(AND(L94="Yes", J94="yes" ),"Yes","No") -> Yes | O94: =SUMIF('raw data'!B$2:B$501,B94,'raw data'!I$2:I$501) -> 2396.8 | P94: =IF(OR(I94<Visualization!$B$6,I94>Visualization!$B$7),"Outlier","Normal") -> Outlier
A95: O10093 | B95: 45227 | C95: C111 | D95: Electronics | E95: P45 | F95: 3 | G95: 1999 | I95: 5997 | J95: =IF(I95>formulas!$B$5,"yes","no") -> yes | K95: =IF(H95>0,"yes","no") -> no | L95: =IF(COUNTIF('raw data'!$B$2:$B$501,B95)>1,"Yes","No") -> No | M95: =IF(H95>15,"yes","no") -> no | N95: =IF(AND(L95="Yes", J95="yes" ),"Yes","No") -> No | O95: =SUMIF('raw data'!B$2:B$501,B95,'raw data'!I$2:I$501) -> 5997 | P95: =IF(OR(I95<Visualization!$B$6,I95>Visualization!$B$7),"Outlier","Normal") -> Outlier
A96: O10094 | B96: 44991 | C96: C124 | D96: Beauty | E96: P96 | F96: 3 | G96: 499 | I96: 1497 | J96: =IF(I96>formulas!$B$5,"yes","no") -> yes | K96: =IF(H96>0,"yes","no") -> no | L96: =IF(COUNTIF('raw data'!$B$2:$B$501,B96)>1,"Yes","No") -> No | M96: =IF(H96>15,"yes","no") -> no | N96: =IF(AND(L96="Yes", J96="yes" ),"Yes","No") -> No | O96: =SUMIF('raw data'!B$2:B$501,B96,'raw data'!I$2:I$501) -> 1497 | P96: =IF(OR(I96<Visualization!$B$6,I96>Visualization!$B$7),"Outlier","Normal") -> Outlier
A97: O10095 | B97: 45271 | C97: C151 | D97: Home | E97: P62 | F97: 3 | G97: 299 | H97: 0 | I97: 897 | J97: =IF(I97>formulas!$B$5,"yes","no") -> no | K97: =IF(H97>0,"yes","no") -> no | L97: =IF(COUNTIF('raw data'!$B$2:$B$501,B97)>1,"Yes","No") -> Yes | M97: =IF(H97>15,"yes","no") -> no | N97: =IF(AND(L97="Yes", J97="yes" ),"Yes","No") -> No | O97: =SUMIF('raw data'!B$2:B$501,B97,'raw data'!I$2:I$501) -> 897 | P97: =IF(OR(I97<Visualization!$B$6,I97>Visualization!$B$7),"Outlier","Normal") -> Outlier
A98: O10096 | B98: 45253 | C98: C184 | D98: Beauty | E98: P93 | F98: 2 | G98: 999 | H98: 20 | I98: 1598.4 | J98: =IF(I98>formulas!$B$5,"yes","no") -> yes | K98: =IF(H98>0,"yes","no") -> yes | L98: =IF(COUNTIF('raw data'!$B$2:$B$501,B98)>1,"Yes","No") -> Yes | M98: =IF(H98>15,"yes","no") -> yes | N98: =IF(AND(L98="Yes", J98="yes" ),"Yes","No") -> Yes | O98: =SUMIF('raw data'!B$2:B$501,B98,'raw data'!I$2:I$501) -> 1956.6 | P98: =IF(OR(I98<Visualization!$B$6,I98>Visualization!$B$7),"Outlier","Normal") -> Outlier
A99: O10097 | B99: 44935 | C99: C199 | D99: Sports | E99: P58 | F99: 2 | G99: 499 | I99: 998 | J99: =IF(I99>formulas!$B$5,"yes","no") -> no | K99: =IF(H99>0,"yes","no") -> no | L99: =IF(COUNTIF('raw data'!$B$2:$B$501,B99)>1,"Yes","No") -> Yes | M99: =IF(H99>15,"yes","no") -> no | N99: =IF(AND(L99="Yes", J99="yes" ),"Yes","No") -> No | O99: =SUMIF('raw data'!B$2:B$501,B99,'raw data'!I$2:I$501) -> 4794.2 | P99: =IF(OR(I99<Visualization!$B$6,I99>Visualization!$B$7),"Outlier","Normal") -> Outlier
A100: O10098 | B100: 45270 | C100: C152 | D100: Electronics | E100: P67 | F100: 3 | G100: 1499 | H100: 0 | I100: 4497 | J100: =IF(I100>formulas!$B$5,"yes","no") -> yes | K100: =IF(H100>0,"yes","no") -> no | L100: =IF(COUNTIF('raw data'!$B$2:$B$501,B100)>1,"Yes","No") -> Yes | M100: =IF(H100>15,"yes","no") -> no | N100: =IF(AND(L100="Yes", J100="yes" ),"Yes","No") -> Yes | O100: =SUMIF('raw data'!B$2:B$501,B100,'raw data'!I$2:I$501) -> 4815.4 | P100: =IF(OR(I100<Visualization!$B$6,I100>Visualization!$B$7),"Outlier","Normal") -> Outlier
...

Sheet formulas
A2: TOTAL REVENUE | B2: =SUM('raw data'!I2:I502,) -> 701382.55
A3: TOTAL ORDERS | B3: {=SUM(1/COUNTIF('raw data'!A2:A501,'raw data'!A2:A501))} -> 500
A4: TOTAL CUSTOMER | B4: {=SUM(1/COUNTIF('raw data'!B2:B501,'raw data'!B2:B501))} -> 267
A5: AVERAGE ORDER VALUE | B5: =B2/B3 -> 1402.7651
A6: AVERAGE ITEM PER ORDER | B6: 2.16
A7: AVERAGE DISCOUNT | B7: =AVERAGE('raw data'!H2:H501) -> 10.383693
A8: REVENUE PER CUSTOMER | B8: =B2/B4 -> 2626.9009
B13: =IF(B5<'raw data'!I3,"yes","no") -> no

Sheet validation
A1: TOTAL REVENUE | B1: Blank revenue rows were ignored by SUM
B3: Only numeric revenue values (408 rows) were aggregated
B5: No error values present in revenue column
B7: Verified all Order_IDs are unique
A10: TOTAL ORDERS | B10: COUNT ignored Order_IDs because they are text
B12: COUNTA used to count non-empty Order_IDs
B14: Verified all Order_IDs are unique
A17: TOTAL CUSTOMER | B17: Identified 267 unique customers
B19: COUNTIF-based uniqueness logic applied
B21: Repeat customers correctly consolidated
A23: AVERAGE ORDER VALUE | B23: Calculated as Total Revenue divided by Total Orders
B25: Uses previously validated KPIs
B27: Represents average spend per order
A29: AVERAGE ITEM PER ORDER | B29: Calculated using total quantity sold
B31: Normalized by unique orders
B33: Indicates basket size behavior
A35: AVERAGE DISCOUNT | B35: Calculated as simple average of discount percentages
B37: Blank values excluded automatically
B39: Indicates pricing & promotion intensity
A41: REVENUE PER CUSTOMER | B41: Calculated using validated Total Revenue and Total Customers
B43: Represents average lifetime spend per customer in dataset
B45: Sensitive to repeat purchase behavior
A49: FLAGS
A50: USING IF
A51: HIGH ORDER VALUE | B51: Used absolute reference to lock AOV threshold
B53: Prevented row-shift errors during drag-down
B55: Ensured consistent comparison logic
A57: DISCOUNTED ORDERS | B57: Flagged orders with any discount applied
B59: Zero-discount orders classified separately
B61: Enables promo vs non-promo analysis
A63: REPEATED CUSTOMERS | B63: Identified customers with multiple orders
B65: COUNTIF-based frequency logic applied
B67: Enables retention and loyalty analysis
A69: HIGH DISCOUNTED ORDERS | B69: Flagged orders where discount > 15%
B71: Threshold is adjustable for business strategy
B73: Supports margin and promotion analysis
A75: VIP CUSTOMERS | B75: Customers with multiple high spend orders → Yes
B77: One-time or low spend customers → No
B79: VIP count < Total Customers

Sheet Visualization
